assets/__init__.py
bcnadds/TgGraph.py
bcnadds/__init__.py
bcnadds/errors.py
bcnadds/file_depreciated.py
bcnadds/funcs.py
bcnadds-0.0.27.dist-info/LICENSE
bcnadds-0.0.27.dist-info/METADATA
bcnadds-0.0.27.dist-info/WHEEL
bcnadds-0.0.27.dist-info/top_level.txt
bcnadds-0.0.27.dist-info/RECORD
