Metadata-Version: 2.1
Name: bcnadds
Version: 0.0.27
Summary: This package for blackcat userbot adds
Home-page: https://github.com/bcncalling/bcnadds
Author: santhosh
Author-email: yumikoapi@gmail.com
Keywords: bcnadds,telegram,telegram-bots,bcn userbot,telegram bots library
Classifier: Development Status :: 5 - Production/Stable
Classifier: Intended Audience :: Developers
Classifier: Natural Language :: English
Classifier: License :: OSI Approved :: GNU Lesser General Public License v3 (LGPLv3)
Classifier: Operating System :: OS Independent
Classifier: Programming Language :: Python
Classifier: Programming Language :: Python :: 3
Classifier: Programming Language :: Python :: 3.7
Classifier: Programming Language :: Python :: 3.8
Classifier: Programming Language :: Python :: 3.9
Classifier: Programming Language :: Python :: 3.10
Classifier: Programming Language :: Python :: 3.11
Classifier: Programming Language :: Python :: Implementation
Classifier: Programming Language :: Python :: Implementation :: CPython
Classifier: Programming Language :: Python :: Implementation :: PyPy
Classifier: Topic :: Internet
Classifier: Topic :: Communications
Classifier: Topic :: Communications :: Chat
Classifier: Topic :: Software Development :: Libraries
Classifier: Topic :: Software Development :: Libraries :: Python Modules
Classifier: Topic :: Software Development :: Libraries :: Application Frameworks
Requires-Python: >=3.6
License-File: LICENSE
Requires-Dist: pyrogram ==2.0.106
Requires-Dist: TgCrypto
Requires-Dist: requests ==2.28.2
Requires-Dist: asyncio ==3.4.3
Requires-Dist: aiofiles
Requires-Dist: aiohttp
Requires-Dist: pillow
Requires-Dist: numpy
Requires-Dist: youtube-search-python
Requires-Dist: youtube-search
Requires-Dist: search-engine-parser
